snowplow_tracker/__init__.py
snowplow_tracker/_version.py
snowplow_tracker/constants.py
snowplow_tracker/contracts.py
snowplow_tracker/emitter_configuration.py
snowplow_tracker/emitters.py
snowplow_tracker/event_store.py
snowplow_tracker/payload.py
snowplow_tracker/py.typed
snowplow_tracker/self_describing_json.py
snowplow_tracker/snowplow.py
snowplow_tracker/subject.py
snowplow_tracker/tracker.py
snowplow_tracker/tracker_configuration.py
snowplow_tracker/typing.py
snowplow_tracker/events/__init__.py
snowplow_tracker/events/event.py
snowplow_tracker/events/page_ping.py
snowplow_tracker/events/page_view.py
snowplow_tracker/events/screen_view.py
snowplow_tracker/events/self_describing.py
snowplow_tracker/events/structured_event.py
snowplow_tracker/test/__init__.py
snowplow_tracker-1.1.0.dist-info/LICENSE
snowplow_tracker-1.1.0.dist-info/METADATA
snowplow_tracker-1.1.0.dist-info/WHEEL
snowplow_tracker-1.1.0.dist-info/top_level.txt
snowplow_tracker-1.1.0.dist-info/RECORD
