Metadata-Version: 2.1
Name: snowplow-tracker
Version: 1.1.0
Summary: Snowplow event tracker for Python. Add analytics to your Python and Django apps, webapps and games
Home-page: http://snowplow.io
Author: Anuj More, Alexander Dean, Fred Blundun, Paul Boocock, Matus Tomlein, Jack Keene
Author-email: support@snowplow.io
License: Apache License 2.0
Classifier: Development Status :: 5 - Production/Stable
Classifier: Intended Audience :: Developers
Classifier: License :: OSI Approved :: Apache Software License
Classifier: Programming Language :: Python
Classifier: Programming Language :: Python :: 3
Classifier: Programming Language :: Python :: 3.8
Classifier: Programming Language :: Python :: 3.9
Classifier: Programming Language :: Python :: 3.10
Classifier: Programming Language :: Python :: 3.11
Classifier: Programming Language :: Python :: 3.12
Classifier: Programming Language :: Python :: 3.13
Classifier: Operating System :: OS Independent
License-File: LICENSE
Requires-Dist: requests<3.0,>=2.25.1
Requires-Dist: typing_extensions>=3.7.4
Provides-Extra: typing
Requires-Dist: mypy>=0.971; extra == "typing"
Requires-Dist: types-requests<3.0,>=2.25.1; extra == "typing"
